CHANGES.txt
LICENSE.txt
README.txt
setup.py
js/__init__.py
js.javascript_load_image.egg-info/PKG-INFO
js.javascript_load_image.egg-info/SOURCES.txt
js.javascript_load_image.egg-info/dependency_links.txt
js.javascript_load_image.egg-info/entry_points.txt
js.javascript_load_image.egg-info/namespace_packages.txt
js.javascript_load_image.egg-info/not-zip-safe
js.javascript_load_image.egg-info/requires.txt
js.javascript_load_image.egg-info/top_level.txt
js/javascript_load_image/__init__.py
js/javascript_load_image/test_javascript_load_image.txt
js/javascript_load_image/resources/load-image.js
js/javascript_load_image/resources/load-image.min.js