Metadata-Version: 1.0
Name: js.javascript-load-image
Version: 1.2.3
Summary: Fanstatic packaging of JavaScript Load Image
Home-page: https://github.com/disko/js.javascript_load_image
Author: Andreas Kaiser
Author-email: disko@binary-punks.com
License: BSD
Platform: UNKNOWN
